CODE_OF_CONDUCT.md
CONTRIBUTING.md
LICENSE
README.rst
setup.cfg
setup.py
docs/changelog.rst
docs/conf.py
docs/doctests.rst
docs/extend.rst
docs/handling.rst
docs/index.rst
docs/installation.rst
docs/license.rst
docs/quickstart.rst
docs/release_notes.rst
docs/static/queue_monitor.png
docs/static/worksheet_queued_analyses_viewlet.png
src/senaite/__init__.py
src/senaite.queue.egg-info/PKG-INFO
src/senaite.queue.egg-info/SOURCES.txt
src/senaite.queue.egg-info/dependency_links.txt
src/senaite.queue.egg-info/entry_points.txt
src/senaite.queue.egg-info/namespace_packages.txt
src/senaite.queue.egg-info/not-zip-safe
src/senaite.queue.egg-info/requires.txt
src/senaite.queue.egg-info/top_level.txt
src/senaite/queue/__init__.py
src/senaite/queue/api.py
src/senaite/queue/configure.zcml
src/senaite/queue/interfaces.py
src/senaite/queue/pasplugin.py
src/senaite/queue/queue.py
src/senaite/queue/request.py
src/senaite/queue/setuphandlers.py
src/senaite/queue/version.txt
src/senaite/queue/adapters/__init__.py
src/senaite/queue/adapters/actions.py
src/senaite/queue/adapters/configure.zcml
src/senaite/queue/adapters/guards.py
src/senaite/queue/adapters/listing.py
src/senaite/queue/browser/__init__.py
src/senaite/queue/browser/configure.zcml
src/senaite/queue/browser/controlpanel.py
src/senaite/queue/browser/static/icon.png
src/senaite/queue/browser/static/queued.gif
src/senaite/queue/browser/viewlets/__init__.py
src/senaite/queue/browser/viewlets/configure.zcml
src/senaite/queue/browser/viewlets/templates/queue_server_status.pt
src/senaite/queue/browser/viewlets/templates/queued_analyses_sample_viewlet.pt
src/senaite/queue/browser/viewlets/templates/queued_analyses_viewlet.pt
src/senaite/queue/browser/views/__init__.py
src/senaite/queue/browser/views/configure.zcml
src/senaite/queue/browser/views/tasks.py
src/senaite/queue/browser/views/worksheet.py
src/senaite/queue/browser/views/templates/tasks.pt
src/senaite/queue/client/__init__.py
src/senaite/queue/client/configure.zcml
src/senaite/queue/client/consumer.py
src/senaite/queue/client/routes.py
src/senaite/queue/client/utility.py
src/senaite/queue/client/views.py
src/senaite/queue/locales/senaite.queue.pot
src/senaite/queue/locales/cs/LC_MESSAGES/senaite.queue.po
src/senaite/queue/locales/de/LC_MESSAGES/senaite.queue.po
