Metadata-Version: 2.1
Name: senaite.queue
Version: 1.0.3
Summary: Asynchronous tasks add-on for SENAITE
Home-page: https://github.com/senaite/senaite.queue
Author: RIDING BYTES & NARALABS
Author-email: senaite@senaite.com
License: GPLv2
Keywords: senaite,lims,opensource
Platform: UNKNOWN
Classifier: Framework :: Plone
Classifier: Framework :: Zope2
Classifier: Programming Language :: Python
Classifier: License :: OSI Approved :: GNU General Public License v2 (GPLv2)
Provides-Extra: test
